mesonpep517-0.2.dist-info/METADATA
mesonpep517-0.2.dist-info/WHEEL
mesonpep517/__init__.py
mesonpep517/buildapi.py
mesonpep517/pep425tags.py
mesonpep517/schema.py
mesonpep517-0.2.dist-info/RECORD
