Metadata-Version: 2.1
Name: mesonpep517
Version: 0.2
Summary: Create pep517 compliant packages from the meson build system
Home-page: https://gitlab.com/thiblahute/mesonpep517
Author: Thibault Saunier
Author-email: tsaunier@gnome.org
Requires-Dist: wheel>0.33
Requires-Dist: meson
Requires-Dist: toml
Requires-Dist: setuptools
Classifier: Intended Audience :: Developers
Classifier: License :: OSI Approved :: Apache Software License
Classifier: Programming Language :: Python :: 3
Classifier: Topic :: Software Development :: Libraries :: Python Modules
Project-URL: Source, https://gitlab.com/thiblahute/mesonpep517
Project-URL: Documentation, https://thiblahute.gitlab.io/mesonpep517/
